ocitools/__init__.py
ocitools/color.py
ocitools/common.py
ocitools/compartment.py
ocitools/compute.py
ocitools/computeclient.py
ocitools/dbs.py
ocitools/dbsclient.py
ocitools/extract.py
ocitools/get_oci_commands.py
ocitools/iam.py
ocitools/iam_nongc.py
ocitools/iamclient.py
ocitools/keys.py
ocitools/keysclient.py
ocitools/misc.py
ocitools/oci_config.py
ocitools/ocicli_wrapper.py
ocitools/ocitools.py
ocitools/ocitools_show.py
ocitools/oss.py
ocitools/ossclient.py
ocitools/regions.py
ocitools/regionsclient.py
ocitools/secrets.py
ocitools/secretsclient.py
ocitools/shapes.py
ocitools/vault.py
ocitools/vaultclient.py
ocitools/archive/add_api_key.py
ocitools/archive/find_storage.py
ocitools/archive/list_instances.py
ocitools/archive/myoss.py
goatocitools-2024.7.16.1623.dist-info/METADATA
goatocitools-2024.7.16.1623.dist-info/WHEEL
goatocitools-2024.7.16.1623.dist-info/entry_points.txt
goatocitools-2024.7.16.1623.dist-info/top_level.txt
goatocitools-2024.7.16.1623.dist-info/RECORD
