Metadata-Version: 2.1
Name: goatocitools
Version: 2024.7.16.1623
Summary: OCItools - CLI client for OCI
Author-email: Chris Stacks <centerupt@gmail.com>
Classifier: Programming Language :: Python :: 3
Classifier: Operating System :: OS Independent
Requires-Python: >=3.7
Requires-Dist: oci
Requires-Dist: oci-cli
Requires-Dist: click >=8.0.4
Requires-Dist: tqdm
Requires-Dist: requests-ntlm
